{
  "version": "5.2.1",
  "flags": {},
  "imagePath": "fra829_001943.jpg",
  "imageData": null,
  "imageHeight": 1090,
  "imageWidth": 1500,
  "shapes": [
    {
      "label": "U盘",
      "points": [
        [
          252.02,
          902.17
        ],
        [
          283.67,
          902.46
        ],
        [
          284.25,
          906.24
        ],
        [
          303.99,
          905.07
        ],
        [
          305.74,
          902.46
        ],
        [
          359.75,
          903.33
        ],
        [
          359.46,
          942.24
        ],
        [
          305.74,
          942.82
        ],
        [
          304.28,
          939.05
        ],
        [
          283.09,
          938.76
        ],
        [
          281.34,
          941.37
        ],
        [
          248.82,
          941.37
        ],
        [
          247.66,
          927.43
        ],
        [
          242.43,
          925.11
        ],
        [
          242.72,
          918.14
        ],
        [
          245.63,
          914.37
        ],
        [
          243.89,
          897.52
        ],
        [
          255.21,
          871.68
        ],
        [
          255.79,
          863.55
        ],
        [
          262.76,
          859.19
        ],
        [
          270.31,
          861.23
        ],
        [
          265.66,
          864.42
        ],
        [
          260.73,
          864.13
        ],
        [
          260.15,
          870.23
        ],
        [
          265.66,
          869.94
        ],
        [
          267.7,
          867.04
        ],
        [
          265.66,
          864.42
        ],
        [
          270.02,
          861.23
        ],
        [
          271.47,
          867.33
        ],
        [
          268.57,
          874.0
        ],
        [
          261.31,
          876.04
        ],
        [
          257.24,
          880.39
        ],
        [
          251.73,
          891.43
        ]
      ],
      "group_id": null,
      "description": "",
      "shape_type": "polygon",
      "flags": {}
    }
  ]
}