{
  "version": "5.2.1",
  "flags": {},
  "imagePath": "Video_20230813105118815__0000953000.jpg",
  "imageData": null,
  "imageHeight": 1090,
  "imageWidth": 1500,
  "shapes": [
    {
      "label": "口红",
      "points": [
        [
          696.3,
          478.2
        ],
        [
          685.91,
          495.36
        ],
        [
          692.45,
          530.65
        ],
        [
          763.02,
          598.61
        ],
        [
          797.0,
          572.47
        ]
      ],
      "group_id": null,
      "description": "",
      "shape_type": "polygon",
      "flags": {}
    },
    {
      "label": "手",
      "points": [
        [
          369.63,
          3.94
        ],
        [
          404.92,
          112.42
        ],
        [
          448.05,
          177.77
        ],
        [
          504.24,
          256.18
        ],
        [
          548.68,
          328.07
        ],
        [
          532.6,
          421.5
        ],
        [
          544.3,
          473.6
        ],
        [
          564.3,
          526.0
        ],
        [
          586.58,
          535.87
        ],
        [
          604.88,
          558.09
        ],
        [
          644.09,
          559.4
        ],
        [
          702.9,
          569.85
        ],
        [
          708.13,
          551.56
        ],
        [
          689.83,
          546.33
        ],
        [
          687.22,
          470.53
        ],
        [
          697.67,
          435.24
        ],
        [
          713.36,
          463.99
        ],
        [
          729.04,
          450.92
        ],
        [
          725.12,
          375.12
        ],
        [
          696.37,
          321.53
        ],
        [
          668.92,
          294.09
        ],
        [
          628.41,
          230.05
        ],
        [
          580.05,
          104.58
        ],
        [
          552.6,
          0.02
        ]
      ],
      "group_id": null,
      "description": "",
      "shape_type": "polygon",
      "flags": {}
    }
  ]
}