{
  "version": "5.2.1",
  "flags": {},
  "imagePath": "Video_20230809132725097__0000042300.jpg",
  "imageData": null,
  "imageHeight": 1090,
  "imageWidth": 1500,
  "shapes": [
    {
      "label": "身份证",
      "points": [
        [
          224.31,
          455.41
        ],
        [
          311.6,
          455.41
        ],
        [
          316.1,
          462.3
        ],
        [
          316.1,
          605.5
        ],
        [
          311.6,
          610.3
        ],
        [
          224.31,
          610.83
        ],
        [
          219.8,
          607.6
        ],
        [
          218.5,
          458.6
        ]
      ],
      "group_id": null,
      "description": "",
      "shape_type": "polygon",
      "flags": {}
    }
  ]
}