{
  "version": "5.2.1",
  "flags": {},
  "imagePath": "Video_20230813105118815__0000945500.jpg",
  "imageData": null,
  "imageHeight": 1090,
  "imageWidth": 1500,
  "shapes": [
    {
      "label": "口红",
      "points": [
        [
          1256.84,
          901.06
        ],
        [
          1237.87,
          903.61
        ],
        [
          1229.84,
          927.69
        ],
        [
          1233.9,
          944.7
        ],
        [
          1262.7,
          961.2
        ],
        [
          1276.53,
          968.18
        ],
        [
          1293.68,
          964.53
        ],
        [
          1302.43,
          951.4
        ],
        [
          1305.35,
          947.02
        ],
        [
          1306.08,
          929.15
        ],
        [
          1290.76,
          918.93
        ]
      ],
      "group_id": null,
      "description": "",
      "shape_type": "polygon",
      "flags": {}
    }
  ]
}