{
  "version": "5.2.1",
  "flags": {},
  "imagePath": "Video_20230819153338915__0000078000.jpg",
  "imageData": null,
  "imageHeight": 1090,
  "imageWidth": 1500,
  "shapes": [
    {
      "label": "水杯",
      "points": [
        [
          1223.7,
          73.0
        ],
        [
          1193.9,
          71.8
        ],
        [
          1178.35,
          73.21
        ],
        [
          1170.16,
          79.41
        ],
        [
          1167.51,
          91.79
        ],
        [
          1168.39,
          112.37
        ],
        [
          1171.27,
          120.33
        ],
        [
          1174.2,
          125.8
        ],
        [
          1163.75,
          149.09
        ],
        [
          1141.85,
          188.24
        ],
        [
          1134.55,
          255.71
        ],
        [
          1129.68,
          334.68
        ],
        [
          1133.5,
          463.8
        ],
        [
          1141.63,
          469.83
        ],
        [
          1154.9,
          472.26
        ],
        [
          1177.68,
          471.82
        ],
        [
          1208.21,
          472.49
        ],
        [
          1232.32,
          472.26
        ],
        [
          1246.7,
          466.73
        ],
        [
          1250.02,
          444.17
        ],
        [
          1250.46,
          402.59
        ],
        [
          1253.11,
          348.61
        ],
        [
          1255.1,
          265.44
        ],
        [
          1257.32,
          194.43
        ],
        [
          1240.06,
          144.44
        ],
        [
          1228.9,
          126.8
        ],
        [
          1229.5,
          120.8
        ],
        [
          1231.6,
          107.4
        ],
        [
          1229.8,
          84.9
        ]
      ],
      "group_id": null,
      "description": "",
      "shape_type": "polygon",
      "flags": {}
    }
  ]
}