{
  "version": "5.2.1",
  "flags": {},
  "imagePath": "Video_20230813105118815__0000338500.jpg",
  "imageData": null,
  "imageHeight": 1090,
  "imageWidth": 1500,
  "shapes": [
    {
      "label": "口红",
      "points": [
        [
          1241.86,
          808.71
        ],
        [
          1233.25,
          813.01
        ],
        [
          1232.39,
          953.38
        ],
        [
          1236.7,
          957.68
        ],
        [
          1272.0,
          959.41
        ],
        [
          1278.89,
          949.93
        ],
        [
          1277.17,
          809.57
        ]
      ],
      "group_id": null,
      "description": "",
      "shape_type": "polygon",
      "flags": {}
    }
  ]
}