{
  "version": "5.2.1",
  "flags": {},
  "imagePath": "Video_20230813090234284__0001062500.jpg",
  "imageData": null,
  "imageHeight": 1090,
  "imageWidth": 1500,
  "shapes": [
    {
      "label": "登机牌",
      "points": [
        [
          633.69,
          811.53
        ],
        [
          639.59,
          805.15
        ],
        [
          883.3,
          797.0
        ],
        [
          888.2,
          800.5
        ],
        [
          892.9,
          942.7
        ],
        [
          888.91,
          944.18
        ],
        [
          646.9,
          952.0
        ],
        [
          640.81,
          950.57
        ],
        [
          635.7,
          946.5
        ],
        [
          632.8,
          943.9
        ],
        [
          631.97,
          848.38
        ],
        [
          632.46,
          816.45
        ]
      ],
      "group_id": null,
      "description": "",
      "shape_type": "polygon",
      "flags": {}
    }
  ]
}