{
  "version": "5.2.1",
  "flags": {},
  "imagePath": "Video_20230813154728550__0000291000.jpg",
  "imageData": null,
  "imageHeight": 1090,
  "imageWidth": 1500,
  "shapes": [
    {
      "label": "电脑",
      "points": [
        [
          233.91,
          353.32
        ],
        [
          588.41,
          342.56
        ],
        [
          599.82,
          347.51
        ],
        [
          607.65,
          355.83
        ],
        [
          608.79,
          363.65
        ],
        [
          608.9,
          447.1
        ],
        [
          605.1,
          454.1
        ],
        [
          595.2,
          482.9
        ],
        [
          582.1,
          503.38
        ],
        [
          561.29,
          543.27
        ],
        [
          555.9,
          572.34
        ],
        [
          556.77,
          597.67
        ],
        [
          556.77,
          613.89
        ],
        [
          565.02,
          629.25
        ],
        [
          563.37,
          654.58
        ],
        [
          563.8,
          683.21
        ],
        [
          569.18,
          705.67
        ],
        [
          574.2,
          716.87
        ],
        [
          584.7,
          720.2
        ],
        [
          593.29,
          713.49
        ],
        [
          598.24,
          703.95
        ],
        [
          606.14,
          681.99
        ],
        [
          606.57,
          655.8
        ],
        [
          608.9,
          694.2
        ],
        [
          608.51,
          947.51
        ],
        [
          607.3,
          957.5
        ],
        [
          604.56,
          964.73
        ],
        [
          601.4,
          969.25
        ],
        [
          595.8,
          975.21
        ],
        [
          480.99,
          969.97
        ],
        [
          256.3,
          960.21
        ],
        [
          231.4,
          958.99
        ],
        [
          223.0,
          956.55
        ],
        [
          216.97,
          951.53
        ],
        [
          210.73,
          946.5
        ],
        [
          208.36,
          941.12
        ],
        [
          206.64,
          788.27
        ],
        [
          207.07,
          384.39
        ],
        [
          207.72,
          373.63
        ],
        [
          209.9,
          366.6
        ],
        [
          213.89,
          362.58
        ],
        [
          219.27,
          357.63
        ],
        [
          224.72,
          355.33
        ]
      ],
      "group_id": null,
      "description": "",
      "shape_type": "polygon",
      "flags": {}
    },
    {
      "label": "手",
      "points": [
        [
          704.7,
          69.3
        ],
        [
          697.45,
          91.98
        ],
        [
          681.69,
          153.29
        ],
        [
          661.11,
          282.2
        ],
        [
          639.49,
          355.57
        ],
        [
          630.54,
          410.95
        ],
        [
          618.05,
          439.79
        ],
        [
          610.64,
          439.88
        ],
        [
          608.9,
          447.1
        ],
        [
          605.1,
          454.1
        ],
        [
          595.2,
          482.9
        ],
        [
          582.1,
          503.38
        ],
        [
          561.29,
          543.27
        ],
        [
          555.9,
          572.34
        ],
        [
          556.77,
          597.67
        ],
        [
          556.77,
          613.89
        ],
        [
          565.02,
          629.25
        ],
        [
          563.37,
          654.58
        ],
        [
          563.8,
          683.21
        ],
        [
          569.18,
          705.67
        ],
        [
          574.2,
          716.87
        ],
        [
          584.7,
          720.2
        ],
        [
          593.29,
          713.49
        ],
        [
          598.24,
          703.95
        ],
        [
          606.14,
          681.99
        ],
        [
          606.57,
          655.8
        ],
        [
          608.9,
          694.2
        ],
        [
          609.5,
          704.9
        ],
        [
          629.93,
          705.8
        ],
        [
          647.76,
          704.68
        ],
        [
          661.37,
          686.68
        ],
        [
          669.2,
          663.35
        ],
        [
          685.3,
          642.2
        ],
        [
          693.92,
          606.42
        ],
        [
          689.61,
          572.75
        ],
        [
          695.29,
          531.76
        ],
        [
          691.16,
          504.47
        ],
        [
          713.29,
          466.75
        ],
        [
          758.24,
          385.8
        ],
        [
          802.08,
          308.38
        ],
        [
          843.3,
          236.1
        ],
        [
          866.6,
          165.4
        ],
        [
          877.43,
          119.02
        ],
        [
          884.14,
          79.84
        ],
        [
          883.1,
          48.3
        ],
        [
          897.1,
          18.0
        ],
        [
          905.4,
          0.0
        ],
        [
          856.7,
          0.0
        ],
        [
          834.1,
          0.0
        ],
        [
          815.7,
          0.0
        ],
        [
          807.5,
          0.0
        ],
        [
          775.3,
          2.2
        ],
        [
          656.5,
          0.8
        ],
        [
          683.7,
          47.3
        ]
      ],
      "group_id": null,
      "description": "",
      "shape_type": "polygon",
      "flags": {}
    }
  ]
}