{
  "version": "5.2.1",
  "flags": {},
  "imagePath": "Video_20230813102655753__0001333500.jpg",
  "imageData": null,
  "imageHeight": 1090,
  "imageWidth": 1500,
  "shapes": [
    {
      "label": "梳子",
      "points": [
        [
          217.89,
          944.24
        ],
        [
          207.91,
          953.69
        ],
        [
          206.86,
          960.52
        ],
        [
          209.49,
          967.35
        ],
        [
          213.16,
          969.98
        ],
        [
          238.38,
          967.88
        ],
        [
          264.11,
          966.3
        ],
        [
          285.12,
          966.3
        ],
        [
          302.98,
          966.3
        ],
        [
          320.84,
          966.83
        ],
        [
          331.87,
          957.37
        ],
        [
          340.27,
          953.17
        ],
        [
          355.5,
          952.6
        ],
        [
          368.6,
          953.2
        ],
        [
          385.4,
          954.2
        ],
        [
          399.1,
          956.3
        ],
        [
          412.8,
          957.4
        ],
        [
          425.4,
          955.8
        ],
        [
          434.81,
          953.17
        ],
        [
          439.02,
          949.49
        ],
        [
          435.34,
          945.29
        ],
        [
          429.56,
          943.19
        ],
        [
          375.46,
          943.19
        ],
        [
          343.42,
          943.19
        ],
        [
          314.53,
          943.19
        ],
        [
          282.5,
          943.19
        ],
        [
          257.81,
          942.66
        ],
        [
          237.33,
          942.66
        ]
      ],
      "group_id": null,
      "description": "",
      "shape_type": "polygon",
      "flags": {}
    }
  ]
}