{
  "version": "5.2.1",
  "flags": {},
  "imagePath": "Video_20230813130953065__0000497500.jpg",
  "imageData": null,
  "imageHeight": 1090,
  "imageWidth": 1500,
  "shapes": [
    {
      "label": "手",
      "points": [
        [
          631.9,
          70.3
        ],
        [
          600.73,
          102.79
        ],
        [
          564.36,
          126.33
        ],
        [
          519.42,
          157.35
        ],
        [
          480.9,
          180.89
        ],
        [
          448.8,
          194.8
        ],
        [
          432.75,
          199.08
        ],
        [
          416.7,
          202.29
        ],
        [
          400.66,
          204.43
        ],
        [
          393.17,
          204.43
        ],
        [
          377.12,
          204.43
        ],
        [
          365.35,
          204.43
        ],
        [
          354.65,
          208.71
        ],
        [
          345.02,
          211.92
        ],
        [
          335.39,
          215.13
        ],
        [
          315.06,
          227.97
        ],
        [
          305.3,
          242.9
        ],
        [
          294.5,
          265.3
        ],
        [
          292.59,
          276.12
        ],
        [
          292.59,
          281.47
        ],
        [
          296.6,
          283.6
        ],
        [
          293.1,
          289.7
        ],
        [
          288.4,
          295.6
        ],
        [
          283.3,
          303.6
        ],
        [
          278.3,
          311.8
        ],
        [
          273.5,
          319.3
        ],
        [
          268.9,
          325.1
        ],
        [
          263.2,
          330.7
        ],
        [
          256.6,
          335.9
        ],
        [
          252.7,
          341.4
        ],
        [
          250.6,
          352.1
        ],
        [
          250.87,
          361.71
        ],
        [
          252.3,
          367.6
        ],
        [
          256.4,
          374.1
        ],
        [
          261.5,
          377.5
        ],
        [
          268.3,
          381.9
        ],
        [
          280.6,
          378.5
        ],
        [
          289.1,
          372.6
        ],
        [
          295.7,
          371.1
        ],
        [
          290.9,
          377.8
        ],
        [
          285.6,
          385.2
        ],
        [
          282.0,
          397.0
        ],
        [
          284.5,
          406.4
        ],
        [
          288.31,
          410.93
        ],
        [
          293.1,
          414.9
        ],
        [
          302.6,
          417.0
        ],
        [
          310.3,
          416.8
        ],
        [
          316.5,
          413.5
        ],
        [
          324.69,
          403.44
        ],
        [
          330.04,
          398.09
        ],
        [
          336.6,
          395.9
        ],
        [
          339.6,
          396.6
        ],
        [
          335.3,
          402.6
        ],
        [
          335.7,
          411.1
        ],
        [
          338.3,
          417.8
        ],
        [
          345.2,
          420.7
        ],
        [
          357.8,
          421.6
        ],
        [
          365.9,
          417.9
        ],
        [
          374.9,
          409.9
        ],
        [
          382.5,
          402.8
        ],
        [
          390.1,
          395.4
        ],
        [
          398.1,
          396.1
        ],
        [
          405.1,
          399.1
        ],
        [
          408.8,
          401.0
        ],
        [
          413.5,
          402.37
        ],
        [
          418.84,
          399.16
        ],
        [
          426.2,
          393.5
        ],
        [
          435.96,
          386.32
        ],
        [
          443.8,
          380.8
        ],
        [
          449.4,
          373.9
        ],
        [
          453.08,
          367.06
        ],
        [
          457.36,
          359.57
        ],
        [
          462.71,
          351.01
        ],
        [
          466.8,
          343.7
        ],
        [
          473.4,
          332.0
        ],
        [
          476.62,
          327.47
        ],
        [
          481.8,
          318.4
        ],
        [
          487.32,
          311.42
        ],
        [
          496.9,
          306.1
        ],
        [
          508.2,
          301.5
        ],
        [
          514.7,
          298.0
        ],
        [
          525.84,
          292.16
        ],
        [
          536.54,
          288.96
        ],
        [
          546.1,
          286.6
        ],
        [
          559.6,
          283.4
        ],
        [
          572.6,
          280.3
        ],
        [
          586.82,
          277.19
        ],
        [
          599.66,
          275.05
        ],
        [
          611.9,
          272.1
        ],
        [
          631.7,
          266.4
        ],
        [
          652.7,
          261.2
        ],
        [
          670.3,
          254.0
        ],
        [
          687.6,
          247.1
        ],
        [
          711.2,
          234.8
        ],
        [
          732.6,
          220.2
        ],
        [
          754.7,
          203.2
        ],
        [
          778.07,
          184.65
        ],
        [
          798.58,
          186.02
        ],
        [
          843.71,
          184.65
        ],
        [
          843.71,
          184.65
        ],
        [
          887.48,
          161.4
        ],
        [
          914.83,
          143.62
        ],
        [
          953.12,
          105.33
        ],
        [
          981.84,
          61.56
        ],
        [
          991.42,
          27.37
        ],
        [
          1002.36,
          0.0
        ],
        [
          644.3,
          0.0
        ],
        [
          638.57,
          50.62
        ]
      ],
      "group_id": null,
      "description": "",
      "shape_type": "polygon",
      "flags": {}
    },
    {
      "label": "手环",
      "points": [
        [
          344.48,
          211.64
        ],
        [
          343.2,
          198.4
        ],
        [
          335.36,
          183.56
        ],
        [
          324.92,
          171.44
        ],
        [
          315.68,
          165.2
        ],
        [
          315.68,
          165.2
        ],
        [
          308.24,
          162.32
        ],
        [
          297.56,
          160.4
        ],
        [
          286.7,
          159.5
        ],
        [
          272.72,
          161.36
        ],
        [
          254.84,
          168.44
        ],
        [
          238.7,
          179.7
        ],
        [
          222.5,
          203.0
        ],
        [
          218.48,
          223.64
        ],
        [
          218.72,
          239.84
        ],
        [
          228.2,
          256.4
        ],
        [
          243.44,
          271.16
        ],
        [
          253.76,
          277.76
        ],
        [
          265.16,
          280.76
        ],
        [
          282.32,
          283.76
        ],
        [
          290.36,
          283.76
        ],
        [
          295.04,
          283.16
        ],
        [
          292.88,
          281.72
        ],
        [
          292.76,
          276.08
        ],
        [
          293.12,
          273.68
        ],
        [
          290.0,
          273.56
        ],
        [
          281.96,
          273.56
        ],
        [
          273.8,
          272.0
        ],
        [
          265.04,
          270.44
        ],
        [
          255.44,
          265.28
        ],
        [
          249.32,
          262.04
        ],
        [
          241.3,
          253.5
        ],
        [
          236.6,
          247.3
        ],
        [
          231.8,
          239.9
        ],
        [
          230.36,
          232.4
        ],
        [
          230.36,
          220.04
        ],
        [
          233.48,
          209.12
        ],
        [
          242.2,
          191.8
        ],
        [
          252.8,
          181.4
        ],
        [
          266.36,
          175.4
        ],
        [
          280.04,
          170.48
        ],
        [
          294.32,
          170.24
        ],
        [
          308.24,
          173.24
        ],
        [
          318.2,
          178.88
        ],
        [
          329.6,
          193.4
        ],
        [
          335.12,
          205.76
        ],
        [
          336.56,
          215.0
        ],
        [
          344.72,
          212.0
        ]
      ],
      "group_id": null,
      "description": "",
      "shape_type": "polygon",
      "flags": {}
    }
  ]
}