{
  "version": "5.2.1",
  "flags": {},
  "imagePath": "wallet_20230816__0001010000.jpg",
  "imageData": null,
  "imageHeight": 1090,
  "imageWidth": 1500,
  "shapes": [
    {
      "label": "钱包",
      "points": [
        [
          339.28,
          774.31
        ],
        [
          306.94,
          775.78
        ],
        [
          301.8,
          775.78
        ],
        [
          298.12,
          767.7
        ],
        [
          310.62,
          764.76
        ],
        [
          317.23,
          762.56
        ],
        [
          329.73,
          759.62
        ],
        [
          326.79,
          750.06
        ],
        [
          349.57,
          743.45
        ],
        [
          401.75,
          724.34
        ],
        [
          439.24,
          711.84
        ],
        [
          472.31,
          695.67
        ],
        [
          500.98,
          677.3
        ],
        [
          512.74,
          664.07
        ],
        [
          507.59,
          655.98
        ],
        [
          489.22,
          656.72
        ],
        [
          460.55,
          664.07
        ],
        [
          427.48,
          678.03
        ],
        [
          391.47,
          702.29
        ],
        [
          353.98,
          728.01
        ],
        [
          324.58,
          746.39
        ],
        [
          326.42,
          749.77
        ],
        [
          330.02,
          760.42
        ],
        [
          344.5,
          752.27
        ],
        [
          390.58,
          738.08
        ],
        [
          440.56,
          721.84
        ],
        [
          472.46,
          707.65
        ],
        [
          497.67,
          692.0
        ],
        [
          513.99,
          678.91
        ],
        [
          520.67,
          667.6
        ],
        [
          519.65,
          654.44
        ],
        [
          514.28,
          648.78
        ],
        [
          495.91,
          646.65
        ],
        [
          451.95,
          655.18
        ],
        [
          421.45,
          671.12
        ],
        [
          398.08,
          688.84
        ],
        [
          373.61,
          706.55
        ],
        [
          345.97,
          724.63
        ],
        [
          318.26,
          741.98
        ],
        [
          305.18,
          753.0
        ],
        [
          286.36,
          754.4
        ],
        [
          286.36,
          763.29
        ],
        [
          283.94,
          769.68
        ],
        [
          264.76,
          765.42
        ],
        [
          236.09,
          769.83
        ],
        [
          218.45,
          784.53
        ],
        [
          216.25,
          797.03
        ],
        [
          219.19,
          842.59
        ],
        [
          217.72,
          913.15
        ],
        [
          218.7,
          966.9
        ],
        [
          230.21,
          964.6
        ],
        [
          325.76,
          962.4
        ],
        [
          414.69,
          963.87
        ],
        [
          510.24,
          963.87
        ],
        [
          544.78,
          965.34
        ],
        [
          559.48,
          967.54
        ],
        [
          560.22,
          954.31
        ],
        [
          557.28,
          846.27
        ],
        [
          559.48,
          783.8
        ],
        [
          552.87,
          779.39
        ],
        [
          536.7,
          777.18
        ],
        [
          453.64,
          772.04
        ],
        [
          399.99,
          774.24
        ]
      ],
      "group_id": null,
      "description": "",
      "shape_type": "polygon",
      "flags": {}
    }
  ]
}